hidori_cli/__init__.py
hidori_cli/apps/__init__.py
hidori_cli/apps/base.py
hidori_cli/apps/hidori.py
hidori_cli/apps/pipeline.py
hidori_cli/commands/__init__.py
hidori_cli/commands/base.py
hidori_cli/commands/hidori.py
hidori_cli/commands/pipeline.py
hidori_cli/commands/pipeline_run.py
hidori_cli/fields/__init__.py
hidori_cli/fields/base.py
hidori_cli/fields/boolean.py
hidori_cli/fields/extra_data.py
hidori_cli/fields/filepath.py
hidori_cli/fields/text.py
hidori_cli/fields/version.py
hidori_cli/py.typed
hidori_common/__init__.py
hidori_common/cli.py
hidori_common/dirs.py
hidori_common/py.typed
hidori_common/typings.py
hidori_core/__init__.py
hidori_core/modules/__init__.py
hidori_core/modules/apt.py
hidori_core/modules/base.py
hidori_core/modules/dnf.py
hidori_core/modules/hello.py
hidori_core/modules/hostname.py
hidori_core/py.typed
hidori_core/schema/__init__.py
hidori_core/schema/base.py
hidori_core/schema/constraints.py
hidori_core/schema/errors.py
hidori_core/schema/fields.py
hidori_core/utils/__init__.py
hidori_core/utils/messenger.py
hidori_pipelines/__init__.py
hidori_pipelines/group.py
hidori_pipelines/pipeline.py
hidori_pipelines/py.typed
hidori_runner/__init__.py
hidori_runner/drivers/__init__.py
hidori_runner/drivers/base.py
hidori_runner/drivers/local.py
hidori_runner/drivers/ssh.py
hidori_runner/drivers/utils.py
hidori_runner/executors/remote.py
hidori_runner/py.typed
hidori_runner/transports/__init__.py
hidori_runner/transports/docker.py
hidori_runner/transports/podman.py
hidori_runner/transports/ssh.py
hidori_runner/transports/utils.py
hidori-0.3.0.dist-info/METADATA
hidori-0.3.0.dist-info/WHEEL
hidori-0.3.0.dist-info/entry_points.txt
hidori-0.3.0.dist-info/RECORD
