Metadata-Version: 2.1
Name: hidori
Version: 0.3.0
Summary: A modern, agentless, zero-dependency system state assurance
Home-page: https://github.com/hidori-dev/hidori
License: MIT
Author: Piotr Szpetkowski
Author-email: piotr.szpetkowski@pyquest.space
Requires-Python: >=3.11,<4.0
Classifier: Development Status :: 2 - Pre-Alpha
Classifier: Environment :: Console
Classifier: Intended Audience :: Developers
Classifier: License :: OSI Approved :: European Union Public Licence 1.2 (EUPL 1.2)
Classifier: License :: OSI Approved :: MIT License
Classifier: Programming Language :: Python :: 3
Classifier: Programming Language :: Python :: 3.11
Classifier: Programming Language :: Python :: 3 :: Only
Classifier: Topic :: System :: Installation/Setup
Project-URL: Bug Tracker, https://github.com/hidori-dev/hidori/issues
Project-URL: Changelog, https://github.com/hidori-dev/hidori/blob/main/CHANGELOG.md
Project-URL: Repository, https://github.com/hidori-dev/hidori
